toolbiox/DeepTools.py
toolbiox/FormatTools.py
toolbiox/GenAnno.py
toolbiox/GenAssembly.py
toolbiox/GenCompare.py
toolbiox/GenFeatAnno.py
toolbiox/GenFeatTools.py
toolbiox/GenomeTools.py
toolbiox/OrthoTools.py
toolbiox/PhylTools.py
toolbiox/QuickPlot.py
toolbiox/ResourceTools.py
toolbiox/SNPTools.py
toolbiox/StruTools.py
toolbiox/Submitter.py
toolbiox/__init__.py
toolbiox/config.py
toolbiox/miRNATools.py
toolbiox/versions.py
toolbiox/api/__init__.py
toolbiox/api/common/__init__.py
toolbiox/api/common/annotation/__init__.py
toolbiox/api/common/annotation/busco.py
toolbiox/api/common/annotation/stringtie.py
toolbiox/api/common/assembly/__init__.py
toolbiox/api/common/assembly/cap3.py
toolbiox/api/common/assembly/trinity.py
toolbiox/api/common/mapping/__init__.py
toolbiox/api/common/mapping/blast.py
toolbiox/api/common/mapping/clustal.py
toolbiox/api/common/mapping/hisat2.py
toolbiox/api/common/mapping/psl.py
toolbiox/api/common/resource/__init__.py
toolbiox/api/common/resource/ftp.py
toolbiox/api/xuyuxing/__init__.py
toolbiox/api/xuyuxing/comp_genome/__init__.py
toolbiox/api/xuyuxing/comp_genome/dlcpar.py
toolbiox/api/xuyuxing/comp_genome/fasttree.py
toolbiox/api/xuyuxing/comp_genome/gene_duplication_count.py
toolbiox/api/xuyuxing/comp_genome/geneloss.py
toolbiox/api/xuyuxing/comp_genome/genepainter.py
toolbiox/api/xuyuxing/comp_genome/generax.py
toolbiox/api/xuyuxing/comp_genome/mcscan.py
toolbiox/api/xuyuxing/comp_genome/orthofinder.py
toolbiox/api/xuyuxing/comp_genome/phylogenomics.py
toolbiox/api/xuyuxing/comp_genome/planttribes.py
toolbiox/api/xuyuxing/comp_genome/planttribes2.py
toolbiox/api/xuyuxing/comp_genome/tmp_mcscanx.py
toolbiox/api/xuyuxing/comp_genome/treebest.py
toolbiox/api/xuyuxing/comp_genome/orthofinder_tree_resolve/__init__.py
toolbiox/api/xuyuxing/comp_genome/orthofinder_tree_resolve/main.py
toolbiox/api/xuyuxing/comp_genome/orthofinder_tree_resolve/newick.py
toolbiox/api/xuyuxing/comp_genome/orthofinder_tree_resolve/resolve.py
ToolBiox-0.0.46.dist-info/LICENSE
ToolBiox-0.0.46.dist-info/METADATA
ToolBiox-0.0.46.dist-info/WHEEL
ToolBiox-0.0.46.dist-info/top_level.txt
ToolBiox-0.0.46.dist-info/RECORD
