Metadata-Version: 2.1
Name: ToolBiox
Version: 0.0.46
Summary: a biological toolkit for genome assembly, annotation and analysis that we have accumulated from our bioinformatics work
Home-page: https://github.com/SouthernCD/ToolBiox
Author: Yuxing Xu
Author-email: xuyuxing@mail.kib.ac.cn
License: UNKNOWN
Platform: UNKNOWN
Requires-Python: >=3.5
License-File: LICENSE
Requires-Dist: bcbio-gff (>=0.6.6)
Requires-Dist: biopython (<=1.80)
Requires-Dist: interlap (>=0.2.6)
Requires-Dist: matplotlib (>=3.5.0)
Requires-Dist: networkx (>=2.4)
Requires-Dist: numpy (>=1.18.1)
Requires-Dist: pandas (>=1.0.1)
Requires-Dist: pyfaidx (>=0.5.5.2)
Requires-Dist: pysam (>=0.21.0)
Requires-Dist: PyVCF3 (>=1.0.3)
Requires-Dist: retry (>=0.9.2)
Requires-Dist: scipy (>=1.4.1)
Requires-Dist: lxml (>=4.4.1)
Requires-Dist: pingouin (>=0.2.7)
Requires-Dist: fitter (>=1.2.3)
Requires-Dist: mlxtend (>=0.17.2)
Requires-Dist: cloudpickle (>=2.2.0)
Requires-Dist: geopandas (>=0.14.3)
Requires-Dist: rasterio (>=1.3.10)
Requires-Dist: shapely (>=2.0.4)
